[
  {
    "hrvatski": "odgristi",
    "deutsch": "abbeißen"
  },
  {
    "hrvatski": "skretati",
    "deutsch": "abbiegen"
  },
  {
    "hrvatski": "predati",
    "deutsch": "abgeben"
  },
  {
    "hrvatski": "ohladiti",
    "deutsch": "abkühlen"
  },
  {
    "hrvatski": "izmjeriti",
    "deutsch": "abmessen"
  },
  {
    "hrvatski": "ukloniti",
    "deutsch": "abräumen"
  },
  {
    "hrvatski": "zaključati",
    "deutsch": "abschließen"
  },
  {
    "hrvatski": "poslati",
    "deutsch": "absenden"
  },
  {
    "hrvatski": "odložiti",
    "deutsch": "abstellen"
  },
  {
    "hrvatski": "oprati",
    "deutsch": "abwaschen"
  },
  {
    "hrvatski": "obrisati",
    "deutsch": "abwischen"
  },
  {
    "hrvatski": "mijenjati",
    "deutsch": "ändern"
  },
  {
    "hrvatski": "dirati",
    "deutsch": "anfassen"
  },
  {
    "hrvatski": "pecati",
    "deutsch": "angeln"
  },
  {
    "hrvatski": "napasti",
    "deutsch": "angreifen"
  },
  {
    "hrvatski": "poslušati",
    "deutsch": "anhören"
  },
  {
    "hrvatski": "zalijepiti",
    "deutsch": "ankleben"
  },
  {
    "hrvatski": "stići",
    "deutsch": "ankommen"
  },
  {
    "hrvatski": "prisloniti",
    "deutsch": "anlehnen"
  },
  {
    "hrvatski": "slagati",
    "deutsch": "anlügen"
  },
  {
    "hrvatski": "nazvati",
    "deutsch": "anrufen"
  },
  {
    "hrvatski": "upaliti",
    "deutsch": "anschalten"
  },
  {
    "hrvatski": "zavezati",
    "deutsch": "anschnallen"
  },
  {
    "hrvatski": "derati se",
    "deutsch": "anschreien"
  },
  {
    "hrvatski": "napregnuti",
    "deutsch": "anstrengen"
  },
  {
    "hrvatski": "prijaviti",
    "deutsch": "anzeigen"
  },
  {
    "hrvatski": "obući",
    "deutsch": "anziehen"
  },
  {
    "hrvatski": "zapaliti",
    "deutsch": "anzünden"
  },
  {
    "hrvatski": "pljeskati",
    "deutsch": "applaudieren"
  },
  {
    "hrvatski": "ljutiti",
    "deutsch": "ärgern"
  },
  {
    "hrvatski": "disati",
    "deutsch": "atmen"
  },
  {
    "hrvatski": "napuhati",
    "deutsch": "aufblasen"
  },
  {
    "hrvatski": "odvinuti",
    "deutsch": "aufdrehen"
  },
  {
    "hrvatski": "pojesti",
    "deutsch": "aufessen"
  },
  {
    "hrvatski": "uhvatiti",
    "deutsch": "auffangen"
  },
  {
    "hrvatski": "objesiti",
    "deutsch": "aufhängen"
  },
  {
    "hrvatski": "podići",
    "deutsch": "aufheben"
  },
  {
    "hrvatski": "prestati",
    "deutsch": "aufhören"
  },
  {
    "hrvatski": "nalijepiti",
    "deutsch": "aufkleben"
  },
  {
    "hrvatski": "napuniti",
    "deutsch": "aufladen"
  },
  {
    "hrvatski": "ostaviti otvoreno",
    "deutsch": "auflassen"
  },
  {
    "hrvatski": "paziti",
    "deutsch": "aufpassen"
  },
  {
    "hrvatski": "pospremiti",
    "deutsch": "aufräumen"
  },
  {
    "hrvatski": "pokupiti",
    "deutsch": "aufsammeln"
  },
  {
    "hrvatski": "otključati",
    "deutsch": "aufschließen"
  },
  {
    "hrvatski": "napisati",
    "deutsch": "aufschreiben"
  },
  {
    "hrvatski": "ustati",
    "deutsch": "aufstehen"
  },
  {
    "hrvatski": "probuditi se",
    "deutsch": "aufwachen"
  },
  {
    "hrvatski": "probuditi",
    "deutsch": "aufwecken"
  },
  {
    "hrvatski": "obrisati",
    "deutsch": "aufwischen"
  },
  {
    "hrvatski": "razlomiti",
    "deutsch": "auseinanderbrechen"
  },
  {
    "hrvatski": "ispuniti",
    "deutsch": "ausfüllen"
  },
  {
    "hrvatski": "posuditi",
    "deutsch": "ausleihen"
  },
  {
    "hrvatski": "odjaviti se",
    "deutsch": "ausloggen"
  },
  {
    "hrvatski": "ugasiti",
    "deutsch": "ausmachen"
  },
  {
    "hrvatski": "oslikati",
    "deutsch": "ausmalen"
  },
  {
    "hrvatski": "raspremiti",
    "deutsch": "auspacken"
  },
  {
    "hrvatski": "isprobati",
    "deutsch": "ausprobieren"
  },
  {
    "hrvatski": "odmoriti",
    "deutsch": "ausruhen"
  },
  {
    "hrvatski": "poskliznuti se",
    "deutsch": "ausrutschen"
  },
  {
    "hrvatski": "naspavati se",
    "deutsch": "ausschlafen"
  },
  {
    "hrvatski": "izići",
    "deutsch": "aussteigen"
  },
  {
    "hrvatski": "izabrati",
    "deutsch": "aussuchen"
  },
  {
    "hrvatski": "iživjeti se",
    "deutsch": "austoben"
  },
  {
    "hrvatski": "popiti",
    "deutsch": "austrinken"
  },
  {
    "hrvatski": "skinuti",
    "deutsch": "ausziehen"
  }
]
