[{"hr":"odgristi","de":"abbeißen"},{"hr":"skretati","de":"abbiegen"},{"hr":"predati","de":"abgeben"},{"hr":"ohladiti","de":"abkühlen"},{"hr":"izmjeriti","de":"abmessen"},{"hr":"ukloniti","de":"abräumen"},{"hr":"zaključati","de":"abschließen"},{"hr":"poslati","de":"absenden"},{"hr":"odložiti","de":"abstellen"},{"hr":"oprati","de":"abwaschen"},{"hr":"obrisati","de":"abwischen"},{"hr":"mijenjati","de":"ändern"},{"hr":"dirati","de":"anfassen"},{"hr":"pecati","de":"angeln"},{"hr":"napasti","de":"angreifen"},{"hr":"poslušati","de":"anhören"},{"hr":"zalijepiti","de":"ankleben"},{"hr":"stići","de":"ankommen"},{"hr":"prisloniti","de":"anlehnen"},{"hr":"slagati","de":"anlügen"},{"hr":"nazvati","de":"anrufen"},{"hr":"upaliti","de":"anschalten"},{"hr":"zavezati","de":"anschnallen"},{"hr":"derati se","de":"anschreien"},{"hr":"napregnuti","de":"anstrengen"},{"hr":"prijaviti","de":"anzeigen"},{"hr":"obući","de":"anziehen"},{"hr":"zapaliti","de":"anzünden"},{"hr":"pljeskati","de":"applaudieren"},{"hr":"ljutiti","de":"ärgern"},{"hr":"disati","de":"atmen"},{"hr":"napuhati","de":"aufblasen"},{"hr":"odvinuti","de":"aufdrehen"},{"hr":"pojesti","de":"aufessen"},{"hr":"uhvatiti","de":"auffangen"},{"hr":"objesiti","de":"aufhängen"},{"hr":"podići","de":"aufheben"},{"hr":"prestati","de":"aufhören"},{"hr":"nalijepiti","de":"aufkleben"},{"hr":"napuniti","de":"aufladen"},{"hr":"ostaviti otvoreno","de":"auflassen"},{"hr":"paziti","de":"aufpassen"},{"hr":"pospremiti","de":"aufräumen"},{"hr":"pokupiti","de":"aufsammeln"},{"hr":"otključati","de":"aufschließen"},{"hr":"napisati","de":"aufschreiben"},{"hr":"ustati","de":"aufstehen"},{"hr":"probuditi se","de":"aufwachen"},{"hr":"probuditi","de":"aufwecken"},{"hr":"obrisati","de":"aufwischen"},{"hr":"razlomiti","de":"auseinanderbrechen"},{"hr":"ispuniti","de":"ausfüllen"},{"hr":"posuditi","de":"ausleihen"},{"hr":"odjaviti se","de":"ausloggen"},{"hr":"ugasiti","de":"ausmachen"},{"hr":"oslikati","de":"ausmalen"},{"hr":"raspremiti","de":"auspacken"},{"hr":"isprobati","de":"ausprobieren"},{"hr":"odmoriti","de":"ausruhen"},{"hr":"poskliznuti se","de":"ausrutschen"},{"hr":"naspavati se","de":"ausschlafen"},{"hr":"izići","de":"aussteigen"},{"hr":"izabrati","de":"aussuchen"},{"hr":"iživjeti se","de":"austoben"},{"hr":"popiti","de":"austrinken"},{"hr":"skinuti","de":"ausziehen"}]
